{
    "rows": {
        "headers": [
            ["10:09", "200", 1],
            ["10:08", "200", 1],

            ["10:07", "200", 2],
            ["10:06", "3550", 4],
            
            ["10:05", "1300", 2]
       ],
        "data": [
            ["10", "10|30.5", "10|0.1", "10|5.2", "10|11", "50|100"],
            ["19", "19", "29", "11", "", " "],

            ["18|10", "20|30.5", "-|0.1", "10|5.2", "20|11", "30|100"],
            ["17", "19", "29", "11", "19", "29"],

            ["16|10", "20|30.5", "-|0.1", "10|5.2", "20|11", "30|100"]
       ]
    },
    "date": "2015-06-15",
    "error": null
}
